docling_cvat_tools/__init__.py
docling_cvat_tools/utils.py
docling_cvat_tools/cli/__init__.py
docling_cvat_tools/cli/cvat_to_docling_cli.py
docling_cvat_tools/cli/cvat_validator_cli.py
docling_cvat_tools/cvat_tools/__init__.py
docling_cvat_tools/cvat_tools/analysis.py
docling_cvat_tools/cvat_tools/cvat_to_docling.py
docling_cvat_tools/cvat_tools/document.py
docling_cvat_tools/cvat_tools/folder_models.py
docling_cvat_tools/cvat_tools/folder_parser.py
docling_cvat_tools/cvat_tools/geometry.py
docling_cvat_tools/cvat_tools/models.py
docling_cvat_tools/cvat_tools/parser.py
docling_cvat_tools/cvat_tools/path_mappings.py
docling_cvat_tools/cvat_tools/tree.py
docling_cvat_tools/cvat_tools/utils.py
docling_cvat_tools/cvat_tools/validator.py
docling_cvat_tools/datamodels/__init__.py
docling_cvat_tools/datamodels/cvat_types.py
docling_cvat_tools/visualisation/__init__.py
docling_cvat_tools/visualisation/constants.py
docling_cvat_tools/visualisation/visualisations.py
docling_cvat_tools-0.0.1.dist-info/licenses/LICENSE
docling_cvat_tools-0.0.1.dist-info/METADATA
docling_cvat_tools-0.0.1.dist-info/WHEEL
docling_cvat_tools-0.0.1.dist-info/entry_points.txt
docling_cvat_tools-0.0.1.dist-info/top_level.txt
docling_cvat_tools-0.0.1.dist-info/RECORD
