Metadata-Version: 2.4
Name: docling-cvat-tools
Version: 0.0.1
Summary: CVAT annotation tools for Docling document processing and evaluation
Author-email: Christoph Auer <cau@zurich.ibm.com>, Panos Vagenas <pva@zurich.ibm.com>, Ahmed Nassar <ahn@zurich.ibm.com>, Nikos Livathinos <nli@zurich.ibm.com>, Maxim Lysak <mly@zurich.ibm.com>, Michele Dolfi <dol@zurich.ibm.com>, Peter Staar <taa@zurich.ibm.com>
License-Expression: MIT
Project-URL: homepage, https://github.com/docling-project/docling-cvat-tools
Project-URL: repository, https://github.com/docling-project/docling-cvat-tools
Project-URL: issues, https://github.com/docling-project/docling-cvat-tools/issues
Keywords: docling,cvat,annotation,evaluation
Classifier: Operating System :: MacOS :: MacOS X
Classifier: Operating System :: POSIX :: Linux
Classifier: Development Status :: 4 - Beta
Classifier: Intended Audience :: Developers
Classifier: Intended Audience :: Science/Research
Classifier: Topic :: Scientific/Engineering :: Artificial Intelligence
Classifier: Programming Language :: Python :: 3
Requires-Python: <4.0,>=3.10
License-File: LICENSE
Requires-Dist: docling-core<3.0.0,>=2.48.0
Requires-Dist: docling<3.0.0,>=2.56.1
Requires-Dist: pydantic<3.0.0,>=2.0.0
Requires-Dist: lxml<6.0.0,>=5.3.0
Requires-Dist: pandas<3.0.0,>=2.2.3
Requires-Dist: openpyxl<4.0.0,>=3.1.5
Requires-Dist: pillow<12.0.0,>=10.3.0
Requires-Dist: tqdm<5.0.0,>=4.67.1
Requires-Dist: typer>=0.16.0
Requires-Dist: cvat-sdk>=2.40.0
Requires-Dist: ocrmac>=1.0.0; sys_platform == "darwin" and platform_machine == "arm64"
Requires-Dist: xlsxwriter>=3.1.0
Dynamic: license-file
